MANIFEST.in
README.rst
setup.py
cuteborg/__init__.py
cuteborg/__main__.py
cuteborg/backend.py
cuteborg/cli.py
cuteborg/config.py
cuteborg/subprocess_backend.py
cuteborg/utils.py
cuteborg/verify.py
cuteborg.egg-info/PKG-INFO
cuteborg.egg-info/SOURCES.txt
cuteborg.egg-info/dependency_links.txt
cuteborg.egg-info/entry_points.txt
cuteborg.egg-info/requires.txt
cuteborg.egg-info/top_level.txt
cuteborg/scheduler/__init__.py
cuteborg/scheduler/__main__.py
cuteborg/scheduler/cli.py
cuteborg/scheduler/core.py
cuteborg/scheduler/devices.py
cuteborg/scheduler/jobs.py
cuteborg/scheduler/protocol.py
cuteborg/scheduler/status.py
cuteborg/scheduler/utils.py
cuteborg/scheduler/wctsleep.py
qtborg/__init__.py
qtborg/utils.py
qtborg/manager/__init__.py
qtborg/manager/__main__.py
qtborg/manager/ui_edit_job.py
qtborg/manager/ui_main.py
qtborg/manager/ui_new_job_wizard.py
qtborg/manager/ui_new_repo_wizard.py
qtborg/manager/ui_prune_widget.py
qtborg/manager/ui_schedule_widget.py
qtborg/trayicon/__init__.py
qtborg/trayicon/__main__.py
qtborg/trayicon/cli.py
qtborg/trayicon/ui_main.py
qtborg/trayicon/data/base.png
qtborg/trayicon/data/bullet_blue.png
qtborg/trayicon/data/bullet_error.png
qtborg/trayicon/data/bullet_green.png
qtborg/trayicon/data/bullet_orange.png
qtborg/trayicon/data/bullet_red.png