Metadata-Version: 1.1
Name: cuteborg
Version: 0.1.3
Summary: Third-party scheduler and UI frontend for Borgbackup
Home-page: https://github.com/horazont/cuteborg
Author: Jonas Wielicki
Author-email: jonas@wielicki.name
License: GPLv3+
Keywords: borgbackup
Platform: UNKNOWN
Classifier: Development Status :: 3 - Alpha
Classifier: Intended Audience :: End Users/Desktop
Classifier: Operating System :: POSIX
Classifier: License :: OSI Approved :: GNU General Public License v3 or later (GPLv3+)
Classifier: Programming Language :: Python :: 3 :: Only
Classifier: Programming Language :: Python :: 3.3
Classifier: Programming Language :: Python :: 3.4
